colbert/__init__.py
colbert/index.py
colbert/index_faiss.py
colbert/index_with_compression.py
colbert/parameters.py
colbert/rerank.py
colbert/retrieve.py
colbert/test.py
colbert/train.py
colbert/evaluation/__init__.py
colbert/evaluation/eval_ranking.py
colbert/evaluation/load_model.py
colbert/evaluation/loaders.py
colbert/evaluation/metrics.py
colbert/evaluation/ranking.py
colbert/evaluation/ranking_logger.py
colbert/evaluation/slow.py
colbert/indexing/__init__.py
colbert/indexing/encoder.py
colbert/indexing/faiss.py
colbert/indexing/faiss_index.py
colbert/indexing/faiss_index_gpu.py
colbert/indexing/index_manager.py
colbert/indexing/loaders.py
colbert/modeling/__init__.py
colbert/modeling/colbert.py
colbert/modeling/colbert_mbert.py
colbert/modeling/colbert_roberta.py
colbert/modeling/colbert_xlmr.py
colbert/modeling/factory.py
colbert/modeling/inference.py
colbert/modeling/tokenization/__init__.py
colbert/modeling/tokenization/doc_tokenization.py
colbert/modeling/tokenization/doc_tokenization_mbert.py
colbert/modeling/tokenization/doc_tokenization_roberta.py
colbert/modeling/tokenization/doc_tokenization_xlmr.py
colbert/modeling/tokenization/query_tokenization.py
colbert/modeling/tokenization/query_tokenization_mbert.py
colbert/modeling/tokenization/query_tokenization_roberta.py
colbert/modeling/tokenization/query_tokenization_xlmr.py
colbert/modeling/tokenization/utils.py
colbert/ranking/__init__.py
colbert/ranking/batch_reranking.py
colbert/ranking/batch_retrieval.py
colbert/ranking/faiss_index.py
colbert/ranking/index_part.py
colbert/ranking/index_ranker.py
colbert/ranking/rankers.py
colbert/ranking/reranking.py
colbert/ranking/retrieval.py
colbert/resources/__init__.py
colbert/training/__init__.py
colbert/training/eager_batcher.py
colbert/training/eager_batcher_2.py
colbert/training/lazy_batcher.py
colbert/training/training.py
colbert/training/utils.py
colbert/utils/__init__.py
colbert/utils/amp.py
colbert/utils/distributed.py
colbert/utils/logging.py
neuralIR-0.0.25.dist-info/LICENSE
neuralIR-0.0.25.dist-info/METADATA
neuralIR-0.0.25.dist-info/WHEEL
neuralIR-0.0.25.dist-info/top_level.txt
neuralIR-0.0.25.dist-info/RECORD
