Metadata-Version: 2.1
Name: neuralIR
Version: 0.0.25
Summary: test package for in-house colbert
Home-page: https://github.ibm.com/mnlp-exp/ColBERT
Author: Yulong Li
Author-email: yulongl@us.ibm.com
License: UNKNOWN
Project-URL: Bug Tracker, https://github.ibm.com/mnlp-exp/ColBERT
Platform: UNKNOWN
Classifier: Programming Language :: Python :: 3
Classifier: License :: OSI Approved :: MIT License
Classifier: Operating System :: OS Independent
Requires-Python: >=3.7
License-File: LICENSE
